<?xml version="1.0" encoding="UTF-8" standalone="yes" ?>


<Uitslag type="Gemeente">
	<Status>Eindstand</Status><DatumTijd>2012-09-13T00:10:15</DatumTijd>
 <Title>
  <Prefix>Gemeente</Prefix>
  <Naam>Alphen aan den Rijn</Naam>
  <Postfix></Postfix>
 </Title>
 <Naam>Gemeente Alphen aan den Rijn</Naam>
 <CBS>0484</CBS>
<KiesKring>15</KiesKring>
 <Provincie>ZH</Provincie>
 <ProvincieNaam>Zuid-Holland</ProvincieNaam>
 <AantalInwoners>72641</AantalInwoners>
 <Stedelijkheid>0</Stedelijkheid>	<Groep type="Totaal">
		<KorteNaam>Kiesger.</KorteNaam>
		<Naam>Kiesgerechtigden</Naam>
		<Verkiezing code="TK12">
			<Stemmen>54900</Stemmen>
		</Verkiezing>
		<Verkiezing code="TK10">
			<Stemmen>55973</Stemmen>
		</Verkiezing>
	</Groep>	<Groep type="Totaal">
		<KorteNaam>Opkomst</KorteNaam>
		<Naam>Opkomst</Naam>
		<Verkiezing code="TK12">
			<Stemmen>41780</Stemmen>
			<Perc>76,1</Perc>
		</Verkiezing>
		<Verkiezing code="TK10">
			<Stemmen>42003</Stemmen>
			<Perc>75,0</Perc>
		</Verkiezing>
	</Groep>	<Groep type="Totaal">
		<KorteNaam>Ongeldig</KorteNaam>
		<Naam>Blanco/ongeldige stemmen</Naam>
		<Verkiezing code="TK12">
			<Stemmen>175</Stemmen>
			<Perc>0,4</Perc>
		</Verkiezing>
		<Verkiezing code="TK10">
			<Stemmen>123</Stemmen>
			<Perc>0,3</Perc>
		</Verkiezing>
	</Groep>	<Groep type="Partij">
		<KorteNaam>VVD</KorteNaam>
		<Naam>Volkspartij voor Vrijheid en Democratie</Naam>
		<Verkiezing code="TK12">
			<Stemmen>13647</Stemmen>
			<Perc>32,8</Perc>
		</Verkiezing>
		<Verkiezing code="TK10">
			<Stemmen>10889</Stemmen>
			<Perc>26,0</Perc>
		</Verkiezing>
	</Groep>	<Groep type="Partij">
		<KorteNaam>PvdA</KorteNaam>
		<Naam>Partij van de Arbeid</Naam>
		<Verkiezing code="TK12">
			<Stemmen>9112</Stemmen>
			<Perc>21,9</Perc>
		</Verkiezing>
		<Verkiezing code="TK10">
			<Stemmen>7198</Stemmen>
			<Perc>17,2</Perc>
		</Verkiezing>
	</Groep>	<Groep type="Partij">
		<KorteNaam>PVV</KorteNaam>
		<Naam>Partij voor de Vrijheid</Naam>
		<Verkiezing code="TK12">
			<Stemmen>3850</Stemmen>
			<Perc>9,3</Perc>
		</Verkiezing>
		<Verkiezing code="TK10">
			<Stemmen>5773</Stemmen>
			<Perc>13,8</Perc>
		</Verkiezing>
	</Groep>	<Groep type="Partij">
		<KorteNaam>CDA</KorteNaam>
		<Naam>Christen-Democratisch Appel</Naam>
		<Verkiezing code="TK12">
			<Stemmen>3228</Stemmen>
			<Perc>7,8</Perc>
		</Verkiezing>
		<Verkiezing code="TK10">
			<Stemmen>5165</Stemmen>
			<Perc>12,3</Perc>
		</Verkiezing>
	</Groep>	<Groep type="Partij">
		<KorteNaam>SP</KorteNaam>
		<Naam>Socialistische Partij</Naam>
		<Verkiezing code="TK12">
			<Stemmen>3035</Stemmen>
			<Perc>7,3</Perc>
		</Verkiezing>
		<Verkiezing code="TK10">
			<Stemmen>3588</Stemmen>
			<Perc>8,6</Perc>
		</Verkiezing>
	</Groep>	<Groep type="Partij">
		<KorteNaam>D66</KorteNaam>
		<Naam>Democraten 66</Naam>
		<Verkiezing code="TK12">
			<Stemmen>3603</Stemmen>
			<Perc>8,7</Perc>
		</Verkiezing>
		<Verkiezing code="TK10">
			<Stemmen>3286</Stemmen>
			<Perc>7,8</Perc>
		</Verkiezing>
	</Groep>	<Groep type="Partij">
		<KorteNaam>GrLinks</KorteNaam>
		<Naam>GroenLinks</Naam>
		<Verkiezing code="TK12">
			<Stemmen>858</Stemmen>
			<Perc>2,1</Perc>
		</Verkiezing>
		<Verkiezing code="TK10">
			<Stemmen>2749</Stemmen>
			<Perc>6,6</Perc>
		</Verkiezing>
	</Groep>	<Groep type="Partij">
		<KorteNaam>CU</KorteNaam>
		<Naam>ChristenUnie</Naam>
		<Verkiezing code="TK12">
			<Stemmen>1656</Stemmen>
			<Perc>4,0</Perc>
		</Verkiezing>
		<Verkiezing code="TK10">
			<Stemmen>1752</Stemmen>
			<Perc>4,2</Perc>
		</Verkiezing>
	</Groep>	<Groep type="Partij">
		<KorteNaam>SGP</KorteNaam>
		<Naam>Staatkundig Gereformeerde Partij</Naam>
		<Verkiezing code="TK12">
			<Stemmen>608</Stemmen>
			<Perc>1,5</Perc>
		</Verkiezing>
		<Verkiezing code="TK10">
			<Stemmen>472</Stemmen>
			<Perc>1,1</Perc>
		</Verkiezing>
	</Groep>	<Groep type="Partij">
		<KorteNaam>PvdD</KorteNaam>
		<Naam>Partij voor de Dieren</Naam>
		<Verkiezing code="TK12">
			<Stemmen>818</Stemmen>
			<Perc>2,0</Perc>
		</Verkiezing>
		<Verkiezing code="TK10">
			<Stemmen>546</Stemmen>
			<Perc>1,3</Perc>
		</Verkiezing>
	</Groep>	<Groep type="Partij">
		<KorteNaam>PPNL</KorteNaam>
		<Naam>PiratenPartij</Naam>
		<Verkiezing code="TK12">
			<Stemmen>159</Stemmen>
			<Perc>0,4</Perc>
		</Verkiezing>
		<Verkiezing code="TK10">
			<Stemmen>38</Stemmen>
			<Perc>0,1</Perc>
		</Verkiezing>
	</Groep>	<Groep type="Partij">
		<KorteNaam>MenS</KorteNaam>
		<Naam>Partij voor Mens en Spirit</Naam>
		<Verkiezing code="TK12">
			<Stemmen>71</Stemmen>
			<Perc>0,2</Perc>
		</Verkiezing>
		<Verkiezing code="TK10">
			<Stemmen>105</Stemmen>
			<Perc>0,3</Perc>
		</Verkiezing>
	</Groep>	<Groep type="Partij">
		<KorteNaam>NL</KorteNaam>
		<Naam>Nederland Lokaal</Naam>
		<Verkiezing code="TK12">
			<Stemmen>7</Stemmen>
			<Perc>0,0</Perc>
		</Verkiezing>
		<Verkiezing code="TK10">
			<Stemmen>-</Stemmen>
			<Perc>-</Perc>
		</Verkiezing>
	</Groep>	<Groep type="Partij">
		<KorteNaam>LP</KorteNaam>
		<Naam>Libertarische Partij</Naam>
		<Verkiezing code="TK12">
			<Stemmen>17</Stemmen>
			<Perc>0,0</Perc>
		</Verkiezing>
		<Verkiezing code="TK10">
			<Stemmen>-</Stemmen>
			<Perc>-</Perc>
		</Verkiezing>
	</Groep>	<Groep type="Partij">
		<KorteNaam>DPK</KorteNaam>
		<Naam>Democratisch Politiek Keerpunt</Naam>
		<Verkiezing code="TK12">
			<Stemmen>32</Stemmen>
			<Perc>0,1</Perc>
		</Verkiezing>
		<Verkiezing code="TK10">
			<Stemmen>-</Stemmen>
			<Perc>-</Perc>
		</Verkiezing>
	</Groep>	<Groep type="Partij">
		<KorteNaam>50+</KorteNaam>
		<Naam>50PLUS</Naam>
		<Verkiezing code="TK12">
			<Stemmen>775</Stemmen>
			<Perc>1,9</Perc>
		</Verkiezing>
		<Verkiezing code="TK10">
			<Stemmen>-</Stemmen>
			<Perc>-</Perc>
		</Verkiezing>
	</Groep>	<Groep type="Partij">
		<KorteNaam>LibDem</KorteNaam>
		<Naam>Liberaal Democratische Partij</Naam>
		<Verkiezing code="TK12">
			<Stemmen>10</Stemmen>
			<Perc>0,0</Perc>
		</Verkiezing>
		<Verkiezing code="TK10">
			<Stemmen>-</Stemmen>
			<Perc>-</Perc>
		</Verkiezing>
	</Groep>	<Groep type="Partij">
		<KorteNaam>AEP</KorteNaam>
		<Naam>Anti Europa Partij</Naam>
		<Verkiezing code="TK12">
			<Stemmen>9</Stemmen>
			<Perc>0,0</Perc>
		</Verkiezing>
		<Verkiezing code="TK10">
			<Stemmen>-</Stemmen>
			<Perc>-</Perc>
		</Verkiezing>
	</Groep>	<Groep type="Partij">
		<KorteNaam>SOPN</KorteNaam>
		<Naam>Soeverein Onafhankelijke Pioniers Nederland</Naam>
		<Verkiezing code="TK12">
			<Stemmen>66</Stemmen>
			<Perc>0,2</Perc>
		</Verkiezing>
		<Verkiezing code="TK10">
			<Stemmen>-</Stemmen>
			<Perc>-</Perc>
		</Verkiezing>
	</Groep>	<Groep type="Partij">
		<KorteNaam>PvdT</KorteNaam>
		<Naam>Partij van de Toekomst</Naam>
		<Verkiezing code="TK12">
			<Stemmen>44</Stemmen>
			<Perc>0,1</Perc>
		</Verkiezing>
		<Verkiezing code="TK10">
			<Stemmen>-</Stemmen>
			<Perc>-</Perc>
		</Verkiezing>
	</Groep>	<Groep type="Partij">
		<KorteNaam>Overige</KorteNaam>
		<Naam>Overige 2010</Naam>
		<Verkiezing code="TK12">
			<Stemmen>-</Stemmen>
			<Perc>-</Perc>
		</Verkiezing>
		<Verkiezing code="TK10">
			<Stemmen>319</Stemmen>
			<Perc>0,8</Perc>
		</Verkiezing>
	</Groep></Uitslag>
