<?xml version="1.0" encoding="UTF-8" standalone="yes" ?>


<Uitslag type="Gemeente">
	<Status>Eindstand</Status><DatumTijd>2012-09-13T14:38:08</DatumTijd>
 <Title>
  <Prefix>Gemeente</Prefix>
  <Naam>De Marne</Naam>
  <Postfix></Postfix>
 </Title>
 <Naam>Gemeente De Marne</Naam>
 <CBS>1663</CBS>
<KiesKring>1</KiesKring>
 <Provincie>GR</Provincie>
 <ProvincieNaam>Groningen</ProvincieNaam>
 <AantalInwoners>10505</AantalInwoners>
 <Stedelijkheid>0</Stedelijkheid>	<Groep type="Totaal">
		<KorteNaam>Kiesger.</KorteNaam>
		<Naam>Kiesgerechtigden</Naam>
		<Verkiezing code="TK12">
			<Stemmen>8190</Stemmen>
		</Verkiezing>
		<Verkiezing code="TK10">
			<Stemmen>8295</Stemmen>
		</Verkiezing>
	</Groep>	<Groep type="Totaal">
		<KorteNaam>Opkomst</KorteNaam>
		<Naam>Opkomst</Naam>
		<Verkiezing code="TK12">
			<Stemmen>6317</Stemmen>
			<Perc>77,1</Perc>
		</Verkiezing>
		<Verkiezing code="TK10">
			<Stemmen>6400</Stemmen>
			<Perc>77,2</Perc>
		</Verkiezing>
	</Groep>	<Groep type="Totaal">
		<KorteNaam>Ongeldig</KorteNaam>
		<Naam>Blanco/ongeldige stemmen</Naam>
		<Verkiezing code="TK12">
			<Stemmen>11</Stemmen>
			<Perc>0,2</Perc>
		</Verkiezing>
		<Verkiezing code="TK10">
			<Stemmen>21</Stemmen>
			<Perc>0,3</Perc>
		</Verkiezing>
	</Groep>	<Groep type="Partij">
		<KorteNaam>VVD</KorteNaam>
		<Naam>Volkspartij voor Vrijheid en Democratie</Naam>
		<Verkiezing code="TK12">
			<Stemmen>1095</Stemmen>
			<Perc>17,4</Perc>
		</Verkiezing>
		<Verkiezing code="TK10">
			<Stemmen>916</Stemmen>
			<Perc>14,4</Perc>
		</Verkiezing>
	</Groep>	<Groep type="Partij">
		<KorteNaam>PvdA</KorteNaam>
		<Naam>Partij van de Arbeid</Naam>
		<Verkiezing code="TK12">
			<Stemmen>1939</Stemmen>
			<Perc>30,7</Perc>
		</Verkiezing>
		<Verkiezing code="TK10">
			<Stemmen>1588</Stemmen>
			<Perc>24,9</Perc>
		</Verkiezing>
	</Groep>	<Groep type="Partij">
		<KorteNaam>PVV</KorteNaam>
		<Naam>Partij voor de Vrijheid</Naam>
		<Verkiezing code="TK12">
			<Stemmen>465</Stemmen>
			<Perc>7,4</Perc>
		</Verkiezing>
		<Verkiezing code="TK10">
			<Stemmen>716</Stemmen>
			<Perc>11,2</Perc>
		</Verkiezing>
	</Groep>	<Groep type="Partij">
		<KorteNaam>CDA</KorteNaam>
		<Naam>Christen-Democratisch Appel</Naam>
		<Verkiezing code="TK12">
			<Stemmen>753</Stemmen>
			<Perc>11,9</Perc>
		</Verkiezing>
		<Verkiezing code="TK10">
			<Stemmen>1050</Stemmen>
			<Perc>16,5</Perc>
		</Verkiezing>
	</Groep>	<Groep type="Partij">
		<KorteNaam>SP</KorteNaam>
		<Naam>Socialistische Partij</Naam>
		<Verkiezing code="TK12">
			<Stemmen>751</Stemmen>
			<Perc>11,9</Perc>
		</Verkiezing>
		<Verkiezing code="TK10">
			<Stemmen>693</Stemmen>
			<Perc>10,9</Perc>
		</Verkiezing>
	</Groep>	<Groep type="Partij">
		<KorteNaam>D66</KorteNaam>
		<Naam>Democraten 66</Naam>
		<Verkiezing code="TK12">
			<Stemmen>281</Stemmen>
			<Perc>4,5</Perc>
		</Verkiezing>
		<Verkiezing code="TK10">
			<Stemmen>202</Stemmen>
			<Perc>3,2</Perc>
		</Verkiezing>
	</Groep>	<Groep type="Partij">
		<KorteNaam>GrLinks</KorteNaam>
		<Naam>GroenLinks</Naam>
		<Verkiezing code="TK12">
			<Stemmen>190</Stemmen>
			<Perc>3,0</Perc>
		</Verkiezing>
		<Verkiezing code="TK10">
			<Stemmen>477</Stemmen>
			<Perc>7,5</Perc>
		</Verkiezing>
	</Groep>	<Groep type="Partij">
		<KorteNaam>CU</KorteNaam>
		<Naam>ChristenUnie</Naam>
		<Verkiezing code="TK12">
			<Stemmen>470</Stemmen>
			<Perc>7,5</Perc>
		</Verkiezing>
		<Verkiezing code="TK10">
			<Stemmen>502</Stemmen>
			<Perc>7,9</Perc>
		</Verkiezing>
	</Groep>	<Groep type="Partij">
		<KorteNaam>SGP</KorteNaam>
		<Naam>Staatkundig Gereformeerde Partij</Naam>
		<Verkiezing code="TK12">
			<Stemmen>65</Stemmen>
			<Perc>1,0</Perc>
		</Verkiezing>
		<Verkiezing code="TK10">
			<Stemmen>39</Stemmen>
			<Perc>0,6</Perc>
		</Verkiezing>
	</Groep>	<Groep type="Partij">
		<KorteNaam>PvdD</KorteNaam>
		<Naam>Partij voor de Dieren</Naam>
		<Verkiezing code="TK12">
			<Stemmen>159</Stemmen>
			<Perc>2,5</Perc>
		</Verkiezing>
		<Verkiezing code="TK10">
			<Stemmen>124</Stemmen>
			<Perc>1,9</Perc>
		</Verkiezing>
	</Groep>	<Groep type="Partij">
		<KorteNaam>PPNL</KorteNaam>
		<Naam>PiratenPartij</Naam>
		<Verkiezing code="TK12">
			<Stemmen>13</Stemmen>
			<Perc>0,2</Perc>
		</Verkiezing>
		<Verkiezing code="TK10">
			<Stemmen>7</Stemmen>
			<Perc>0,1</Perc>
		</Verkiezing>
	</Groep>	<Groep type="Partij">
		<KorteNaam>MenS</KorteNaam>
		<Naam>Partij voor Mens en Spirit</Naam>
		<Verkiezing code="TK12">
			<Stemmen>11</Stemmen>
			<Perc>0,2</Perc>
		</Verkiezing>
		<Verkiezing code="TK10">
			<Stemmen>24</Stemmen>
			<Perc>0,4</Perc>
		</Verkiezing>
	</Groep>	<Groep type="Partij">
		<KorteNaam>NL</KorteNaam>
		<Naam>Nederland Lokaal</Naam>
		<Verkiezing code="TK12">
			<Stemmen>2</Stemmen>
			<Perc>0,0</Perc>
		</Verkiezing>
		<Verkiezing code="TK10">
			<Stemmen>-</Stemmen>
			<Perc>-</Perc>
		</Verkiezing>
	</Groep>	<Groep type="Partij">
		<KorteNaam>LP</KorteNaam>
		<Naam>Libertarische Partij</Naam>
		<Verkiezing code="TK12">
			<Stemmen>1</Stemmen>
			<Perc>0,0</Perc>
		</Verkiezing>
		<Verkiezing code="TK10">
			<Stemmen>-</Stemmen>
			<Perc>-</Perc>
		</Verkiezing>
	</Groep>	<Groep type="Partij">
		<KorteNaam>DPK</KorteNaam>
		<Naam>Democratisch Politiek Keerpunt</Naam>
		<Verkiezing code="TK12">
			<Stemmen>5</Stemmen>
			<Perc>0,1</Perc>
		</Verkiezing>
		<Verkiezing code="TK10">
			<Stemmen>-</Stemmen>
			<Perc>-</Perc>
		</Verkiezing>
	</Groep>	<Groep type="Partij">
		<KorteNaam>50+</KorteNaam>
		<Naam>50PLUS</Naam>
		<Verkiezing code="TK12">
			<Stemmen>88</Stemmen>
			<Perc>1,4</Perc>
		</Verkiezing>
		<Verkiezing code="TK10">
			<Stemmen>-</Stemmen>
			<Perc>-</Perc>
		</Verkiezing>
	</Groep>	<Groep type="Partij">
		<KorteNaam>LibDem</KorteNaam>
		<Naam>Liberaal Democratische Partij</Naam>
		<Verkiezing code="TK12">
			<Stemmen>0</Stemmen>
			<Perc>0,0</Perc>
		</Verkiezing>
		<Verkiezing code="TK10">
			<Stemmen>-</Stemmen>
			<Perc>-</Perc>
		</Verkiezing>
	</Groep>	<Groep type="Partij">
		<KorteNaam>AEP</KorteNaam>
		<Naam>Anti Europa Partij</Naam>
		<Verkiezing code="TK12">
			<Stemmen>7</Stemmen>
			<Perc>0,1</Perc>
		</Verkiezing>
		<Verkiezing code="TK10">
			<Stemmen>-</Stemmen>
			<Perc>-</Perc>
		</Verkiezing>
	</Groep>	<Groep type="Partij">
		<KorteNaam>SOPN</KorteNaam>
		<Naam>Soeverein Onafhankelijke Pioniers Nederland</Naam>
		<Verkiezing code="TK12">
			<Stemmen>7</Stemmen>
			<Perc>0,1</Perc>
		</Verkiezing>
		<Verkiezing code="TK10">
			<Stemmen>-</Stemmen>
			<Perc>-</Perc>
		</Verkiezing>
	</Groep>	<Groep type="Partij">
		<KorteNaam>PvdT</KorteNaam>
		<Naam>Partij van de Toekomst</Naam>
		<Verkiezing code="TK12">
			<Stemmen>4</Stemmen>
			<Perc>0,1</Perc>
		</Verkiezing>
		<Verkiezing code="TK10">
			<Stemmen>-</Stemmen>
			<Perc>-</Perc>
		</Verkiezing>
	</Groep>	<Groep type="Partij">
		<KorteNaam>Overige</KorteNaam>
		<Naam>Overige 2010</Naam>
		<Verkiezing code="TK12">
			<Stemmen>-</Stemmen>
			<Perc>-</Perc>
		</Verkiezing>
		<Verkiezing code="TK10">
			<Stemmen>41</Stemmen>
			<Perc>0,6</Perc>
		</Verkiezing>
	</Groep></Uitslag>
