<?xml version="1.0" encoding="UTF-8" standalone="yes" ?>


<Uitslag type="Gemeente">
	<Status>Eindstand</Status><DatumTijd>2012-09-13T13:44:27</DatumTijd>
 <Title>
  <Prefix>Gemeente</Prefix>
  <Naam>Lingewaard</Naam>
  <Postfix></Postfix>
 </Title>
 <Naam>Gemeente Lingewaard</Naam>
 <CBS>1705</CBS>
<KiesKring>7</KiesKring>
 <Provincie>GE</Provincie>
 <ProvincieNaam>Gelderland</ProvincieNaam>
 <AantalInwoners>45524</AantalInwoners>
 <Stedelijkheid>0</Stedelijkheid>	<Groep type="Totaal">
		<KorteNaam>Kiesger.</KorteNaam>
		<Naam>Kiesgerechtigden</Naam>
		<Verkiezing code="TK12">
			<Stemmen>35174</Stemmen>
		</Verkiezing>
		<Verkiezing code="TK10">
			<Stemmen>34839</Stemmen>
		</Verkiezing>
	</Groep>	<Groep type="Totaal">
		<KorteNaam>Opkomst</KorteNaam>
		<Naam>Opkomst</Naam>
		<Verkiezing code="TK12">
			<Stemmen>26818</Stemmen>
			<Perc>76,2</Perc>
		</Verkiezing>
		<Verkiezing code="TK10">
			<Stemmen>26878</Stemmen>
			<Perc>77,2</Perc>
		</Verkiezing>
	</Groep>	<Groep type="Totaal">
		<KorteNaam>Ongeldig</KorteNaam>
		<Naam>Blanco/ongeldige stemmen</Naam>
		<Verkiezing code="TK12">
			<Stemmen>0</Stemmen>
			<Perc>0,0</Perc>
		</Verkiezing>
		<Verkiezing code="TK10">
			<Stemmen>64</Stemmen>
			<Perc>0,2</Perc>
		</Verkiezing>
	</Groep>	<Groep type="Partij">
		<KorteNaam>VVD</KorteNaam>
		<Naam>Volkspartij voor Vrijheid en Democratie</Naam>
		<Verkiezing code="TK12">
			<Stemmen>8288</Stemmen>
			<Perc>30,9</Perc>
		</Verkiezing>
		<Verkiezing code="TK10">
			<Stemmen>6031</Stemmen>
			<Perc>22,5</Perc>
		</Verkiezing>
	</Groep>	<Groep type="Partij">
		<KorteNaam>PvdA</KorteNaam>
		<Naam>Partij van de Arbeid</Naam>
		<Verkiezing code="TK12">
			<Stemmen>6629</Stemmen>
			<Perc>24,7</Perc>
		</Verkiezing>
		<Verkiezing code="TK10">
			<Stemmen>4676</Stemmen>
			<Perc>17,4</Perc>
		</Verkiezing>
	</Groep>	<Groep type="Partij">
		<KorteNaam>PVV</KorteNaam>
		<Naam>Partij voor de Vrijheid</Naam>
		<Verkiezing code="TK12">
			<Stemmen>2580</Stemmen>
			<Perc>9,6</Perc>
		</Verkiezing>
		<Verkiezing code="TK10">
			<Stemmen>4272</Stemmen>
			<Perc>15,9</Perc>
		</Verkiezing>
	</Groep>	<Groep type="Partij">
		<KorteNaam>CDA</KorteNaam>
		<Naam>Christen-Democratisch Appel</Naam>
		<Verkiezing code="TK12">
			<Stemmen>2435</Stemmen>
			<Perc>9,1</Perc>
		</Verkiezing>
		<Verkiezing code="TK10">
			<Stemmen>4676</Stemmen>
			<Perc>17,4</Perc>
		</Verkiezing>
	</Groep>	<Groep type="Partij">
		<KorteNaam>SP</KorteNaam>
		<Naam>Socialistische Partij</Naam>
		<Verkiezing code="TK12">
			<Stemmen>3029</Stemmen>
			<Perc>11,3</Perc>
		</Verkiezing>
		<Verkiezing code="TK10">
			<Stemmen>3040</Stemmen>
			<Perc>11,3</Perc>
		</Verkiezing>
	</Groep>	<Groep type="Partij">
		<KorteNaam>D66</KorteNaam>
		<Naam>Democraten 66</Naam>
		<Verkiezing code="TK12">
			<Stemmen>2078</Stemmen>
			<Perc>7,7</Perc>
		</Verkiezing>
		<Verkiezing code="TK10">
			<Stemmen>1744</Stemmen>
			<Perc>6,5</Perc>
		</Verkiezing>
	</Groep>	<Groep type="Partij">
		<KorteNaam>GrLinks</KorteNaam>
		<Naam>GroenLinks</Naam>
		<Verkiezing code="TK12">
			<Stemmen>464</Stemmen>
			<Perc>1,7</Perc>
		</Verkiezing>
		<Verkiezing code="TK10">
			<Stemmen>1663</Stemmen>
			<Perc>6,2</Perc>
		</Verkiezing>
	</Groep>	<Groep type="Partij">
		<KorteNaam>CU</KorteNaam>
		<Naam>ChristenUnie</Naam>
		<Verkiezing code="TK12">
			<Stemmen>154</Stemmen>
			<Perc>0,6</Perc>
		</Verkiezing>
		<Verkiezing code="TK10">
			<Stemmen>191</Stemmen>
			<Perc>0,7</Perc>
		</Verkiezing>
	</Groep>	<Groep type="Partij">
		<KorteNaam>SGP</KorteNaam>
		<Naam>Staatkundig Gereformeerde Partij</Naam>
		<Verkiezing code="TK12">
			<Stemmen>37</Stemmen>
			<Perc>0,1</Perc>
		</Verkiezing>
		<Verkiezing code="TK10">
			<Stemmen>24</Stemmen>
			<Perc>0,1</Perc>
		</Verkiezing>
	</Groep>	<Groep type="Partij">
		<KorteNaam>PvdD</KorteNaam>
		<Naam>Partij voor de Dieren</Naam>
		<Verkiezing code="TK12">
			<Stemmen>382</Stemmen>
			<Perc>1,4</Perc>
		</Verkiezing>
		<Verkiezing code="TK10">
			<Stemmen>260</Stemmen>
			<Perc>1,0</Perc>
		</Verkiezing>
	</Groep>	<Groep type="Partij">
		<KorteNaam>PPNL</KorteNaam>
		<Naam>PiratenPartij</Naam>
		<Verkiezing code="TK12">
			<Stemmen>54</Stemmen>
			<Perc>0,2</Perc>
		</Verkiezing>
		<Verkiezing code="TK10">
			<Stemmen>11</Stemmen>
			<Perc>0,0</Perc>
		</Verkiezing>
	</Groep>	<Groep type="Partij">
		<KorteNaam>MenS</KorteNaam>
		<Naam>Partij voor Mens en Spirit</Naam>
		<Verkiezing code="TK12">
			<Stemmen>47</Stemmen>
			<Perc>0,2</Perc>
		</Verkiezing>
		<Verkiezing code="TK10">
			<Stemmen>55</Stemmen>
			<Perc>0,2</Perc>
		</Verkiezing>
	</Groep>	<Groep type="Partij">
		<KorteNaam>NL</KorteNaam>
		<Naam>Nederland Lokaal</Naam>
		<Verkiezing code="TK12">
			<Stemmen>5</Stemmen>
			<Perc>0,0</Perc>
		</Verkiezing>
		<Verkiezing code="TK10">
			<Stemmen>-</Stemmen>
			<Perc>-</Perc>
		</Verkiezing>
	</Groep>	<Groep type="Partij">
		<KorteNaam>LP</KorteNaam>
		<Naam>Libertarische Partij</Naam>
		<Verkiezing code="TK12">
			<Stemmen>6</Stemmen>
			<Perc>0,0</Perc>
		</Verkiezing>
		<Verkiezing code="TK10">
			<Stemmen>-</Stemmen>
			<Perc>-</Perc>
		</Verkiezing>
	</Groep>	<Groep type="Partij">
		<KorteNaam>DPK</KorteNaam>
		<Naam>Democratisch Politiek Keerpunt</Naam>
		<Verkiezing code="TK12">
			<Stemmen>24</Stemmen>
			<Perc>0,1</Perc>
		</Verkiezing>
		<Verkiezing code="TK10">
			<Stemmen>-</Stemmen>
			<Perc>-</Perc>
		</Verkiezing>
	</Groep>	<Groep type="Partij">
		<KorteNaam>50+</KorteNaam>
		<Naam>50PLUS</Naam>
		<Verkiezing code="TK12">
			<Stemmen>525</Stemmen>
			<Perc>2,0</Perc>
		</Verkiezing>
		<Verkiezing code="TK10">
			<Stemmen>-</Stemmen>
			<Perc>-</Perc>
		</Verkiezing>
	</Groep>	<Groep type="Partij">
		<KorteNaam>LibDem</KorteNaam>
		<Naam>Liberaal Democratische Partij</Naam>
		<Verkiezing code="TK12">
			<Stemmen>1</Stemmen>
			<Perc>0,0</Perc>
		</Verkiezing>
		<Verkiezing code="TK10">
			<Stemmen>-</Stemmen>
			<Perc>-</Perc>
		</Verkiezing>
	</Groep>	<Groep type="Partij">
		<KorteNaam>AEP</KorteNaam>
		<Naam>Anti Europa Partij</Naam>
		<Verkiezing code="TK12">
			<Stemmen>5</Stemmen>
			<Perc>0,0</Perc>
		</Verkiezing>
		<Verkiezing code="TK10">
			<Stemmen>-</Stemmen>
			<Perc>-</Perc>
		</Verkiezing>
	</Groep>	<Groep type="Partij">
		<KorteNaam>SOPN</KorteNaam>
		<Naam>Soeverein Onafhankelijke Pioniers Nederland</Naam>
		<Verkiezing code="TK12">
			<Stemmen>35</Stemmen>
			<Perc>0,1</Perc>
		</Verkiezing>
		<Verkiezing code="TK10">
			<Stemmen>-</Stemmen>
			<Perc>-</Perc>
		</Verkiezing>
	</Groep>	<Groep type="Partij">
		<KorteNaam>PvdT</KorteNaam>
		<Naam>Partij van de Toekomst</Naam>
		<Verkiezing code="TK12">
			<Stemmen>40</Stemmen>
			<Perc>0,1</Perc>
		</Verkiezing>
		<Verkiezing code="TK10">
			<Stemmen>-</Stemmen>
			<Perc>-</Perc>
		</Verkiezing>
	</Groep>	<Groep type="Partij">
		<KorteNaam>Overige</KorteNaam>
		<Naam>Overige 2010</Naam>
		<Verkiezing code="TK12">
			<Stemmen>-</Stemmen>
			<Perc>-</Perc>
		</Verkiezing>
		<Verkiezing code="TK10">
			<Stemmen>171</Stemmen>
			<Perc>0,6</Perc>
		</Verkiezing>
	</Groep></Uitslag>
